Course Project/Verilog/CLA5.v
module cla_5bit_nand_only (
    output reg cout,
    output reg [4:0] sum,
    input [4:0] a_in, b_in,
    input cin,
    input clk
);

    reg [4:0] a, b;
    reg [4:0] sum_comb;

    // Sample inputs on clock
    always @(posedge clk) begin
        a <= a_in;
        b <= b_in;
    end

    // NAND Logic Gates as Tasks (Using assign blocks instead of invalid function bodies)
    function automatic nand2(input x, input y);
        nand2 = ~(x & y);
    endfunction

    function automatic inv(input x);
        inv = ~(x & x);
    endfunction

    function automatic and2(input x, input y);
        and2 = ~(~(x & y));
    endfunction

    function automatic or2(input x, input y);
        or2 = ~((~x) & (~y));
    endfunction

    function automatic xor2(input x, input y);
        reg n1, n2, n3;
        begin
            n1 = ~(x & y);
            n2 = ~(x & n1);
            n3 = ~(y & n1);
            xor2 = ~(n2 & n3);
        end
    endfunction

    // Combinational logic
    wire [4:0] g, p;
    wire c0, c1, c2, c3, c4;

    assign g[0] = and2(a[0], b[0]);
    assign g[1] = and2(a[1], b[1]);
    assign g[2] = and2(a[2], b[2]);
    assign g[3] = and2(a[3], b[3]);
    assign g[4] = and2(a[4], b[4]);

    assign p[0] = xor2(a[0], b[0]);
    assign p[1] = xor2(a[1], b[1]);
    assign p[2] = xor2(a[2], b[2]);
    assign p[3] = xor2(a[3], b[3]);
    assign p[4] = xor2(a[4], b[4]);

    assign c0 = or2(g[0], and2(p[0], cin));
    assign c1 = or2(or2(g[1], and2(p[1], g[0])), and2(p[1] & p[0], cin));
    assign c2 = or2(or2(g[2], and2(p[2], g[1])), or2(and2(p[2] & p[1], g[0]), and2(p[2] & p[1] & p[0], cin)));
    assign c3 = or2(or2(g[3], and2(p[3], g[2])),
              or2(and2(p[3] & p[2], g[1]),
              or2(and2(p[3] & p[2] & p[1], g[0]),
                  and2(p[3] & p[2] & p[1] & p[0], cin))));
    assign c4 = or2(or2(g[4], and2(p[4], g[3])),
              or2(and2(p[4] & p[3], g[2]),
              or2(and2(p[4] & p[3] & p[2], g[1]),
              or2(and2(p[4] & p[3] & p[2] & p[1], g[0]),
                  and2(p[4] & p[3] & p[2] & p[1] & p[0], cin)))));

    always @(*) begin
        sum_comb[0] = xor2(p[0], cin);
        sum_comb[1] = xor2(p[1], c0);
        sum_comb[2] = xor2(p[2], c1);
        sum_comb[3] = xor2(p[3], c2);
        sum_comb[4] = xor2(p[4], c3);
    end

    always @(posedge clk) begin
        sum <= sum_comb;
        cout <= c4;
    end

endmodule

Course Project/Verilog/CLA5_tb.v
`timescale 1ns / 1ps

module cla_5bit_nand_only_tb;
    reg [4:0] a_in, b_in;
    reg cin, clk;
    wire [4:0] sum;
    wire cout;

    // instantiate DUT
    cla_5bit_nand_only uut (
        .cout(cout),
        .sum(sum),
        .a_in(a_in),
        .b_in(b_in),
        .cin(cin),
        .clk(clk)
    );

    // 10 timeunit clock period
    initial begin
        clk = 0;
        forever #5 clk = ~clk;
    end

    // print helper showing before/after sampling
    task print_before(input [4:0] ai, input [4:0] bi, input c);
        begin
            $display("\nT=%0t APPLY inputs a_in=%b b_in=%b cin=%b (will be sampled on next posedge)", $time, ai, bi, c);
            $display("  registered a=%b b=%b  sum(reg)=%b cout=%b", uut.a, uut.b, sum, cout);
        end
    endtask

    task print_after_sample();
        begin
            $display("\nT=%0t AFTER posedge (inputs sampled): a=%b b=%b", $time, uut.a, uut.b);
            $display("  combinational sum_comb=%b cout(comb)=%b  (sum reg still previous until next posedge)", uut.sum_comb, uut.cout);
        end
    endtask

    task print_after_output();
        begin
            $display("\nT=%0t AFTER next posedge (outputs registered): sum=%b cout=%b", $time, sum, cout);
        end
    endtask

    initial begin
        $dumpfile("cla_tb.vcd");
        $dumpvars(0, cla_5bit_nand_only_tb);

        // vector 0
        a_in = 5'b00000; b_in = 5'b00000; cin = 0;
        #2; print_before(a_in, b_in, cin);
        @(posedge clk); #1; print_after_sample();
        @(posedge clk); #1; print_after_output();

        // vector 1
        a_in = 5'b00001; b_in = 5'b00001; cin = 0;
        #2; print_before(a_in, b_in, cin);
        @(posedge clk); #1; print_after_sample();
        @(posedge clk); #1; print_after_output();

        // vector 2
        a_in = 5'b01111; b_in = 5'b00001; cin = 0;
        #2; print_before(a_in, b_in, cin);
        @(posedge clk); #1; print_after_sample();
        @(posedge clk); #1; print_after_output();

        // vector 3
        a_in = 5'b10101; b_in = 5'b01010; cin = 0;
        #2; print_before(a_in, b_in, cin);
        @(posedge clk); #1; print_after_sample();
        @(posedge clk); #1; print_after_output();

        // vector 4
        a_in = 5'b11111; b_in = 5'b11111; cin = 0;
        #2; print_before(a_in, b_in, cin);
        @(posedge clk); #1; print_after_sample();
        @(posedge clk); #1; print_after_output();

        #20;
        $finish;
    end

    initial begin
        $monitor("T=%0t a_in=%b b_in=%b cin=%b | sum=%b cout=%b", $time, a_in, b_in, cin, sum, cout);
    end
endmodule

Course Project/Verilog/cla_tb.vcd
$date
	Thu Dec 04 07:43:27 2025
$end
$version
	Icarus Verilog
$end
$timescale
	1ps
$end
$scope module cla_5bit_nand_only_tb $end
$var wire 5 ! sum [4:0] $end
$var wire 1 " cout $end
$var reg 5 # a_in [4:0] $end
$var reg 5 $ b_in [4:0] $end
$var reg 1 % cin $end
$var reg 1 & clk $end
$scope module uut $end
$var wire 5 ' a_in [4:0] $end
$var wire 5 ( b_in [4:0] $end
$var wire 1 % cin $end
$var wire 1 & clk $end
$var wire 5 ) p [4:0] $end
$var wire 5 * g [4:0] $end
$var wire 1 + c4 $end
$var wire 1 , c3 $end
$var wire 1 - c2 $end
$var wire 1 . c1 $end
$var wire 1 / c0 $end
$var reg 5 0 a [4:0] $end
$var reg 5 1 b [4:0] $end
$var reg 1 " cout $end
$var reg 5 2 sum [4:0] $end
$var reg 5 3 sum_comb [4:0] $end
$scope function and2 $end
$upscope $end
$scope function inv $end
$upscope $end
$scope function nand2 $end
$upscope $end
$scope function or2 $end
$upscope $end
$scope function xor2 $end
$upscope $end
$upscope $end
$scope task print_after_output $end
$upscope $end
$scope task print_after_sample $end
$upscope $end
$scope task print_before $end
$var reg 5 4 ai [4:0] $end
$var reg 5 5 bi [4:0] $end
$var reg 1 6 c $end
$upscope $end
$upscope $end
$enddefinitions $end
$comment Show the parameter values. $end
$dumpall
$end
#0
$dumpvars
x6
bx 5
bx 4
bx 3
bx 2
bx 1
bx 0
x/
x.
x-
x,
x+
bx *
bx )
b0 (
b0 '
0&
0%
b0 $
b0 #
x"
bx !
$end
#2000
06
b0 5
b0 4
#5000
0+
0,
0-
0.
0/
b0 3
b0 *
b0 )
b0 1
b0 0
1&
#10000
0&
#15000
0"
b0 !
b0 2
1&
#16000
b1 $
b1 (
b1 #
b1 '
#18000
b1 5
b1 4
#20000
0&
#25000
b10 3
1/
b1 *
b1 1
b1 0
1&
#30000
0&
#35000
b10 !
b10 2
1&
#36000
b1111 #
b1111 '
#38000
b1111 4
#40000
0&
#45000
1,
1-
1.
b10000 3
b1110 )
b1111 0
1&
#50000
0&
#55000
b10000 !
b10000 2
1&
#56000
b1010 $
b1010 (
b10101 #
b10101 '
#58000
b1010 5
b10101 4
#60000
0&
#65000
0,
0.
0-
0/
b11111 3
b0 *
b11111 )
b1010 1
b10101 0
1&
#70000
0&
#75000
b11111 !
b11111 2
1&
#76000
b11111 $
b11111 (
b11111 #
b11111 '
#78000
b11111 5
b11111 4
#80000
0&
#85000
1-
1+
1.
1,
1/
b11110 3
b11111 *
b0 )
b11111 1
b11111 0
1&
#90000
0&
#95000
1"
b11110 !
b11110 2
1&
